MANIFEST.in
README.md
setup.py
nlp/.DS_Store
nlp/MLmodel
nlp/Untitled.ipynb
nlp/conda.yaml
nlp/load_model_from_package.py
nlp/sparkml/metadata/_SUCCESS
nlp/sparkml/metadata/part-00000
nlp/sparkml/stages/0_StringIndexer_ec912f410913/data/_SUCCESS
nlp/sparkml/stages/0_StringIndexer_ec912f410913/data/_committed_586620115825169525
nlp/sparkml/stages/0_StringIndexer_ec912f410913/data/_started_586620115825169525
nlp/sparkml/stages/0_StringIndexer_ec912f410913/data/part-00000-tid-586620115825169525-34f50fae-909e-4db6-b9d9-a696680bd2bb-6918-1-c000.snappy.parquet
nlp/sparkml/stages/0_StringIndexer_ec912f410913/metadata/_SUCCESS
nlp/sparkml/stages/0_StringIndexer_ec912f410913/metadata/part-00000
nlp/sparkml/stages/1_VectorIndexer_55093c9aa1b5/data/_SUCCESS
nlp/sparkml/stages/1_VectorIndexer_55093c9aa1b5/data/_committed_7128410538506238798
nlp/sparkml/stages/1_VectorIndexer_55093c9aa1b5/data/_started_7128410538506238798
nlp/sparkml/stages/1_VectorIndexer_55093c9aa1b5/data/part-00000-tid-7128410538506238798-8e1d491d-7abf-4939-9c60-2e82572f4a9f-6921-1-c000.snappy.parquet
nlp/sparkml/stages/1_VectorIndexer_55093c9aa1b5/metadata/_SUCCESS
nlp/sparkml/stages/1_VectorIndexer_55093c9aa1b5/metadata/part-00000
nlp/sparkml/stages/2_DecisionTreeClassifier_42a9bc8dcd3b/data/_SUCCESS
nlp/sparkml/stages/2_DecisionTreeClassifier_42a9bc8dcd3b/data/_committed_2070705333307468658
nlp/sparkml/stages/2_DecisionTreeClassifier_42a9bc8dcd3b/data/_started_2070705333307468658
nlp/sparkml/stages/2_DecisionTreeClassifier_42a9bc8dcd3b/data/part-00000-tid-2070705333307468658-d80066d8-be89-4d55-8be2-e094329dc4cd-6923-1-c000.snappy.parquet
nlp/sparkml/stages/2_DecisionTreeClassifier_42a9bc8dcd3b/data/part-00001-tid-2070705333307468658-d80066d8-be89-4d55-8be2-e094329dc4cd-6924-1-c000.snappy.parquet
nlp/sparkml/stages/2_DecisionTreeClassifier_42a9bc8dcd3b/data/part-00002-tid-2070705333307468658-d80066d8-be89-4d55-8be2-e094329dc4cd-6925-1-c000.snappy.parquet
nltkPackagedevops.egg-info/PKG-INFO
nltkPackagedevops.egg-info/SOURCES.txt
nltkPackagedevops.egg-info/dependency_links.txt
nltkPackagedevops.egg-info/requires.txt
nltkPackagedevops.egg-info/top_level.txt
