Metadata-Version: 2.1
Name: nltkPackagedevops
Version: 0.0.33
Summary: A small example package
Home-page: https://github.com/kondisettyravi/nltkTransformer
Author: Ravi Teja Kondisetty
Author-email: kondisettyravi@gmail.com
License: UNKNOWN
Platform: UNKNOWN
Classifier: Programming Language :: Python :: 3
Classifier: License :: OSI Approved :: MIT License
Classifier: Operating System :: OS Independent
Requires-Python: >=3.7
